gator/models/__init__.py
gator/models/base_types.py
gator/models/common.py
gator/models/timetable.py
gator/schemas/common.py
gator/schemas/timetable.py
gator_models-1.1.3.dist-info/LICENSE
gator_models-1.1.3.dist-info/WHEEL
gator_models-1.1.3.dist-info/METADATA
gator_models-1.1.3.dist-info/RECORD
