Metadata-Version: 2.1
Name: gator-models
Version: 1.1.3
Summary: MongoDB models for Gator API
Author: Shon Verch
Author-email: verchshon@gmail.com
Requires-Python: >=3.9,<4.0
Classifier: Programming Language :: Python :: 3
Classifier: Programming Language :: Python :: 3.10
Classifier: Programming Language :: Python :: 3.9
Requires-Dist: marshmallow (>=3.17.0,<4.0.0)
Requires-Dist: marshmallow-enum (>=1.5.1,<2.0.0)
Requires-Dist: mongoengine (>=0.20)
